wmmhr/__init__.py
wmmhr/build.py
wmmhr/uncertainty.py
wmmhr/coefs/WMMHR.COF
wmmhr-1.2.3.dist-info/licenses/LICENSE
wmmhr-1.2.3.dist-info/METADATA
wmmhr-1.2.3.dist-info/WHEEL
wmmhr-1.2.3.dist-info/top_level.txt
wmmhr-1.2.3.dist-info/RECORD
