Metadata-Version: 2.4
Name: wmmhr
Version: 1.2.3
Summary: WMMHR Python Module
Author-email: Collin Kadlecek <collin.kadlecek@noaa.gov>, Li-Yin Young <liyin.young@noaa.gov>
Maintainer-email: Collin Kadlecek <collin.kadlecek@noaa.gov>, Li-Yin Young <liyin.young@noaa.gov>
Project-URL: Homepage, https://www.ncei.noaa.gov/products/world-magnetic-model-high-resolution
Project-URL: Repositories, https://github.com/CIRES-Geomagnetism/wmmhr
Classifier: Programming Language :: Python :: 3
Classifier: Programming Language :: Python :: 3.9
Classifier: Programming Language :: Python :: 3.10
Classifier: Programming Language :: Python :: 3.11
Classifier: Programming Language :: Python :: 3.12
Classifier: Programming Language :: Python :: 3.13
Classifier: License :: OSI Approved :: MIT License
Classifier: Operating System :: OS Independent
Requires-Python: >=3.9
License-File: LICENSE
Requires-Dist: numpy
Requires-Dist: geomaglib>=1.2.1
Requires-Dist: wmm-calculator>=1.4.2
Dynamic: license-file
